{
  "generated_at": "2026-06-23T15:20:03-0600",
  "stats": {
    "today_count": 4,
    "today_species": 2,
    "total": 257
  },
  "enviro": {
    "temp_f": 90.1,
    "humidity": 25.0,
    "pressure": 832.8
  },
  "detections": [
    {
      "com_name": "House Finch",
      "sci_name": "Haemorhous mexicanus",
      "confidence": 0.8278,
      "iso": "2026-06-23T09:58:20",
      "time": "09:58",
      "date": "2026-06-23",
      "image": "https://upload.wikimedia.org/wikipedia/commons/thumb/f/f1/House_finch_%2833688%292.jpg/330px-House_finch_%2833688%292.jpg",
      "audio": "bird-clips/House_Finch-83-2026-06-23-birdnet-09.58.20.mp3"
    },
    {
      "com_name": "House Finch",
      "sci_name": "Haemorhous mexicanus",
      "confidence": 0.6586,
      "iso": "2026-06-23T08:23:11",
      "time": "08:23",
      "date": "2026-06-23",
      "image": "https://upload.wikimedia.org/wikipedia/commons/thumb/f/f1/House_finch_%2833688%292.jpg/330px-House_finch_%2833688%292.jpg",
      "audio": "bird-clips/House_Finch-66-2026-06-23-birdnet-08.23.11.mp3"
    },
    {
      "com_name": "Broad-tailed Hummingbird",
      "sci_name": "Selasphorus platycercus",
      "confidence": 0.6816,
      "iso": "2026-06-23T07:09:18",
      "time": "07:09",
      "date": "2026-06-23",
      "image": "https://upload.wikimedia.org/wikipedia/commons/thumb/d/d3/Male_Broad-tailed_Hummingbird_1.jpg/330px-Male_Broad-tailed_Hummingbird_1.jpg",
      "audio": "bird-clips/Broad-tailed_Hummingbird-68-2026-06-23-birdnet-07.09.18.mp3"
    },
    {
      "com_name": "House Finch",
      "sci_name": "Haemorhous mexicanus",
      "confidence": 0.7046,
      "iso": "2026-06-23T06:26:27",
      "time": "06:26",
      "date": "2026-06-23",
      "image": "https://upload.wikimedia.org/wikipedia/commons/thumb/f/f1/House_finch_%2833688%292.jpg/330px-House_finch_%2833688%292.jpg",
      "audio": "bird-clips/House_Finch-70-2026-06-23-birdnet-06.26.27.mp3"
    },
    {
      "com_name": "Broad-tailed Hummingbird",
      "sci_name": "Selasphorus platycercus",
      "confidence": 0.9337,
      "iso": "2026-06-22T05:52:36",
      "time": "05:52",
      "date": "2026-06-22",
      "image": "https://upload.wikimedia.org/wikipedia/commons/thumb/d/d3/Male_Broad-tailed_Hummingbird_1.jpg/330px-Male_Broad-tailed_Hummingbird_1.jpg",
      "audio": "bird-clips/Broad-tailed_Hummingbird-93-2026-06-22-birdnet-05.52.36.mp3"
    },
    {
      "com_name": "House Finch",
      "sci_name": "Haemorhous mexicanus",
      "confidence": 0.711,
      "iso": "2026-06-22T05:42:17",
      "time": "05:42",
      "date": "2026-06-22",
      "image": "https://upload.wikimedia.org/wikipedia/commons/thumb/f/f1/House_finch_%2833688%292.jpg/330px-House_finch_%2833688%292.jpg",
      "audio": "bird-clips/House_Finch-71-2026-06-22-birdnet-05.42.17.mp3"
    },
    {
      "com_name": "House Finch",
      "sci_name": "Haemorhous mexicanus",
      "confidence": 0.8921,
      "iso": "2026-06-22T05:40:53",
      "time": "05:40",
      "date": "2026-06-22",
      "image": "https://upload.wikimedia.org/wikipedia/commons/thumb/f/f1/House_finch_%2833688%292.jpg/330px-House_finch_%2833688%292.jpg",
      "audio": "bird-clips/House_Finch-89-2026-06-22-birdnet-05.40.53.mp3"
    },
    {
      "com_name": "House Finch",
      "sci_name": "Haemorhous mexicanus",
      "confidence": 0.7626,
      "iso": "2026-06-22T05:40:23",
      "time": "05:40",
      "date": "2026-06-22",
      "image": "https://upload.wikimedia.org/wikipedia/commons/thumb/f/f1/House_finch_%2833688%292.jpg/330px-House_finch_%2833688%292.jpg",
      "audio": "bird-clips/House_Finch-76-2026-06-22-birdnet-05.40.23.mp3"
    },
    {
      "com_name": "House Finch",
      "sci_name": "Haemorhous mexicanus",
      "confidence": 0.6801,
      "iso": "2026-06-22T05:40:20",
      "time": "05:40",
      "date": "2026-06-22",
      "image": "https://upload.wikimedia.org/wikipedia/commons/thumb/f/f1/House_finch_%2833688%292.jpg/330px-House_finch_%2833688%292.jpg",
      "audio": "bird-clips/House_Finch-68-2026-06-22-birdnet-05.40.20.mp3"
    },
    {
      "com_name": "House Finch",
      "sci_name": "Haemorhous mexicanus",
      "confidence": 0.7211,
      "iso": "2026-06-22T05:39:02",
      "time": "05:39",
      "date": "2026-06-22",
      "image": "https://upload.wikimedia.org/wikipedia/commons/thumb/f/f1/House_finch_%2833688%292.jpg/330px-House_finch_%2833688%292.jpg",
      "audio": "bird-clips/House_Finch-72-2026-06-22-birdnet-05.39.02.mp3"
    },
    {
      "com_name": "House Finch",
      "sci_name": "Haemorhous mexicanus",
      "confidence": 0.7274,
      "iso": "2026-06-22T05:38:08",
      "time": "05:38",
      "date": "2026-06-22",
      "image": "https://upload.wikimedia.org/wikipedia/commons/thumb/f/f1/House_finch_%2833688%292.jpg/330px-House_finch_%2833688%292.jpg",
      "audio": "bird-clips/House_Finch-73-2026-06-22-birdnet-05.38.08.mp3"
    },
    {
      "com_name": "House Finch",
      "sci_name": "Haemorhous mexicanus",
      "confidence": 0.6668,
      "iso": "2026-06-22T05:37:56",
      "time": "05:37",
      "date": "2026-06-22",
      "image": "https://upload.wikimedia.org/wikipedia/commons/thumb/f/f1/House_finch_%2833688%292.jpg/330px-House_finch_%2833688%292.jpg",
      "audio": "bird-clips/House_Finch-67-2026-06-22-birdnet-05.37.56.mp3"
    },
    {
      "com_name": "House Finch",
      "sci_name": "Haemorhous mexicanus",
      "confidence": 0.7401,
      "iso": "2026-06-22T05:37:08",
      "time": "05:37",
      "date": "2026-06-22",
      "image": "https://upload.wikimedia.org/wikipedia/commons/thumb/f/f1/House_finch_%2833688%292.jpg/330px-House_finch_%2833688%292.jpg",
      "audio": "bird-clips/House_Finch-74-2026-06-22-birdnet-05.37.08.mp3"
    },
    {
      "com_name": "House Finch",
      "sci_name": "Haemorhous mexicanus",
      "confidence": 0.7599,
      "iso": "2026-06-22T05:37:02",
      "time": "05:37",
      "date": "2026-06-22",
      "image": "https://upload.wikimedia.org/wikipedia/commons/thumb/f/f1/House_finch_%2833688%292.jpg/330px-House_finch_%2833688%292.jpg",
      "audio": "bird-clips/House_Finch-76-2026-06-22-birdnet-05.37.02.mp3"
    },
    {
      "com_name": "House Finch",
      "sci_name": "Haemorhous mexicanus",
      "confidence": 0.6832,
      "iso": "2026-06-22T05:36:32",
      "time": "05:36",
      "date": "2026-06-22",
      "image": "https://upload.wikimedia.org/wikipedia/commons/thumb/f/f1/House_finch_%2833688%292.jpg/330px-House_finch_%2833688%292.jpg",
      "audio": "bird-clips/House_Finch-68-2026-06-22-birdnet-05.36.32.mp3"
    }
  ]
}
